survey_monkey/Client.py
survey_monkey/__init__.py
survey_monkey/endpoints.json
survey_monkey/helpers/Constants.py
survey_monkey/helpers/Exceptions.py
survey_monkey/helpers/Util.py
survey_monkey/helpers/__init__.py
survey_monkey_api-0.0.2.dist-info/METADATA
survey_monkey_api-0.0.2.dist-info/RECORD
survey_monkey_api-0.0.2.dist-info/WHEEL
survey_monkey_api-0.0.2.dist-info/top_level.txt
