Metadata-Version: 2.1
Name: survey-monkey-api
Version: 0.0.2
Summary: A simple Python client for the Survey Monkey API (v3).
Home-page: UNKNOWN
Author: Alistair O'Brien
Author-email: alistair@duneroot.co.uk
License: UNKNOWN
Platform: UNKNOWN
Requires-Dist: requests
